telekey/__init__.py
telekey/__main__.py
telekey/decorators.py
telekey/page.py
telekey/tools.py
telekey/telekeyproject/.gitignore
telekey/telekeyproject/bot.py
telekey/telekeyproject/requirements.txt
telekey/telekeyproject/app/__init__.py
telekey/telekeyproject/app/hanlders.py
telekey/telekeyproject/app/models.py
telekey/telekeyproject/app/pages.py
telekey/telekeyproject/app/views.py
telekey-0.1.12.dist-info/LICENSE
telekey-0.1.12.dist-info/METADATA
telekey-0.1.12.dist-info/WHEEL
telekey-0.1.12.dist-info/entry_points.txt
telekey-0.1.12.dist-info/top_level.txt
telekey-0.1.12.dist-info/RECORD
