Metadata-Version: 2.1
Name: telekey
Version: 0.1.12
Summary: An Easy way to develop telegram bots
Home-page: https://github.com/danialkeimasi/telekey
Author: Danial Keimasi
Author-email: danialkeimasi@gmail.com
License: MIT
Platform: UNKNOWN
Classifier: License :: OSI Approved :: MIT License
Classifier: Programming Language :: Python
Classifier: Programming Language :: Python :: 3
Requires-Dist: python-telegram-bot
Requires-Dist: peewee
Requires-Dist: importlib-resources
Requires-Dist: click
